{
  "28100": ["^出席", "", "^(（|議事に参与した)", "欠"],
  "28201": ["^出席議員", "^欠席議員", "^事務局職員出席者", ""],
  "28202": ["", "", ""],
  "28203": ["^〇出席", "^〇欠席", "〇出席説明員", ""],
  "28204": ["^(出席|■出席)", "^(欠席|■欠席)", "^(説明のため|■理事者|■説明員|■地方自治法第105条による出席)", ""],
  "28205": ["会議に出席した議員", "会議に欠席した議員", "会議に出席した説明員", ""],
  "28206": ["^◯出席議員|出席者", "^◯欠席議員|委員外", "^◯会議に出席した吏員及び委員|傍聴", ""],
  "28207": ["^〇.*に出席した", "^〇.*に出席しなかった", "〇職務のため出席した事務局職員の職氏名|〇協議した事項", ""],
  "28208": ["出席議員", "欠席議員", "平成", ""],
  "28209": ["^出席議員", "欠席議員", "欠員", ""],
  "28210": ["出席した.*員", "欠席した.*員", "職員|会議録", ""],
  "28212": ["会議に出席した議員|出席者", "会議に出席しなかった議員|欠席者", "職員|傍聴", ""],
  "28213": ["出席(議|委)員", "欠席(議|委)員", "事務局職員職氏名|説明のため出席した者の職氏名", ""],
  "28214": ["出席議員", "欠席議員", "職員", ""],
  "28215": ["出席議員", "欠席議員", "△|〇", ""],
  "28216": ["^〇出席議員", "^〇欠席議員", "〇", ""],
  "28217": ["出席(議|委)員$", "欠席", "◯", ""],
  "28218": ["会議に出席した議員$", "会議に欠席した議員・説明員$", "職員$", ""],
  "28219": ["^(会議に出席した議員|分科会に出席した委員)", "^(会議に欠席した議員|分科会に欠席した委員)", "職員|職氏名", ""],
  "28220": ["(^▲会議に出席した議員|出席委員$)", "(^▲会議に出席しなかった議員|欠席委員$)", "^▲.*職氏名$|執行者", ""],
  "28221": ["^〇出席議員", "^〇欠席議員", "^〇.*職氏名", ""],
  "28222": ["^(○開会日に応招した議員|出席委員)", "^(○応招しなかった議員|欠席委員)", "議事日程・名簿|^事務局出席職員職氏名"],
  "28223": ["^出席(議|委)員", "^欠席(議|委)員", "議事に関係した議会職員|議会職員", ""],
  "28224": ["^出席議員", "^欠席議員", "欠員", ""],
  "28225": ["^出席議員", "^欠席議員", "欠員", ""],
  "28226": ["会議に出席した議員", "会議に欠席した議員", "会議に出席した事務局員の職氏名", ""],
  "28227": ["^出席(議|委)員", "^欠席議員", "職務のために議場に出席した者の職氏名|出席説明員", ""],
  "28228": ["出席議員|^出席した委員", "欠席議員", "説明のため出席した理事者|傍聴人", ""],
  "28229": ["^会議に出席した議員", "会議に欠席した議員", "議事に関係した事務局職員", ""],
  "26100": [""],
  "26201": [""],
  "26202": [""],
  "26203": [""],
  "26204": [""],
  "26205": [""],
  "26206": [""],
  "26207": [""],
  "26208": [""],
  "26209": [""],
  "26210": [""],
  "26211": [""],
  "26212": [""],
  "26213": [""],
  "26214": [""]
}
